pyredengine/__init__.py
pyredengine/__pycache__/app.cpython-39.pyc
pyredengine/__pycache__/globals.cpython-39.pyc
pyredengine/libs/DebugService.py
pyredengine/libs/EntityService.py
pyredengine/libs/Formatter.py
pyredengine/libs/GuiService.py
pyredengine/libs/NetworkService.py
pyredengine/libs/SceneService.py
pyredengine/libs/TransitionService.py
pyredengine/libs/TweenService.py
pyredengine/libs/Utils.py
pyredengine/libs/__pycache__/DebugService.cpython-39.pyc
pyredengine/libs/__pycache__/EntityService.cpython-39.pyc
pyredengine/libs/__pycache__/Formatter.cpython-39.pyc
pyredengine/libs/__pycache__/GuiService.cpython-39.pyc
pyredengine/libs/__pycache__/NetworkService.cpython-39.pyc
pyredengine/libs/__pycache__/SceneService.cpython-39.pyc
pyredengine/libs/__pycache__/TransitionService.cpython-39.pyc
pyredengine/libs/__pycache__/TweenService.cpython-39.pyc
pyredengine/libs/__pycache__/Utils.cpython-39.pyc
pyredengine/libs/__pycache__/entity.cpython-39.pyc
pyredengine/libs/__pycache__/globals.cpython-39.pyc
pyredengine/resources/font.ttf
pyredengine-0.0.1.3.dist-info/LICENSE.txt
pyredengine-0.0.1.3.dist-info/METADATA
pyredengine-0.0.1.3.dist-info/WHEEL
pyredengine-0.0.1.3.dist-info/top_level.txt
pyredengine-0.0.1.3.dist-info/RECORD
