Metadata-Version: 2.1
Name: pyredengine
Version: 0.0.1.3
Summary: A simple pygame game engine
Author: RedEgs
Author-email: tothemuun21@gmail.com
License: MIT
Project-URL: Source, https://github.com/RedEgs/PyRedEngine
Keywords: engine
Classifier: Development Status :: 5 - Production/Stable
Classifier: Intended Audience :: Education
Classifier: Operating System :: Microsoft :: Windows :: Windows 10
Classifier: License :: OSI Approved :: MIT License
Classifier: Programming Language :: Python :: 3.9
Requires-Python: > 3.8, < 3.11
License-File: LICENSE.txt
Requires-Dist: pygame-ce
Requires-Dist: pytweening
